covid19dh/__init__.py
covid19dh/_cache.py
covid19dh/_cite.py
covid19dh/main.py
covid19dh-2.3.1.dist-info/LICENSE
covid19dh-2.3.1.dist-info/METADATA
covid19dh-2.3.1.dist-info/WHEEL
covid19dh-2.3.1.dist-info/top_level.txt
covid19dh-2.3.1.dist-info/RECORD
