Metadata-Version: 2.1
Name: covid19dh
Version: 2.3.1
Summary: Unified data hub for a better understanding of COVID-19 https://covid19datahub.io
Home-page: https://www.covid19datahub.io
Download-URL: https://github.com/covid19datahub/Python/archive/2.3.0.tar.gz
Author: Martin Beneš
Author-email: martinbenes1996@gmail.com
Keywords: 2019-nCov,coronavirus,covid-19,covid-data,covid19-data
Classifier: Development Status :: 5 - Production/Stable
Classifier: Intended Audience :: Science/Research
Classifier: Intended Audience :: Developers
Classifier: Intended Audience :: Other Audience
Classifier: Topic :: Database
Classifier: Topic :: Scientific/Engineering
Classifier: Topic :: Scientific/Engineering :: Information Analysis
Classifier: Topic :: Software Development :: Libraries
Classifier: Topic :: Utilities
Classifier: License :: OSI Approved :: MIT License
Classifier: Programming Language :: Python :: 3
Classifier: Programming Language :: Python :: 3.8
Classifier: Programming Language :: Python :: 3.9
Classifier: Programming Language :: Python :: 3.10
License-File: LICENSE
Requires-Dist: pandas
Requires-Dist: requests
